ai_query/__init__.py
ai_query/model.py
ai_query/py.typed
ai_query/types.py
ai_query/agents/__init__.py
ai_query/agents/base.py
ai_query/agents/chat.py
ai_query/agents/events.py
ai_query/agents/message.py
ai_query/agents/output.py
ai_query/agents/router.py
ai_query/agents/server.py
ai_query/agents/transport.py
ai_query/agents/websocket.py
ai_query/agents/builtin/__init__.py
ai_query/agents/builtin/durable.py
ai_query/agents/builtin/memory.py
ai_query/agents/builtin/sqlite.py
ai_query/mcp/__init__.py
ai_query/mcp/client.py
ai_query/mcp/transports.py
ai_query/mcp/types.py
ai_query/mcp/utils.py
ai_query/providers/__init__.py
ai_query/providers/base.py
ai_query/providers/anthropic/__init__.py
ai_query/providers/anthropic/provider.py
ai_query/providers/bedrock/__init__.py
ai_query/providers/bedrock/provider.py
ai_query/providers/deepseek/__init__.py
ai_query/providers/deepseek/provider.py
ai_query/providers/google/__init__.py
ai_query/providers/google/provider.py
ai_query/providers/groq/__init__.py
ai_query/providers/groq/provider.py
ai_query/providers/llama/__init__.py
ai_query/providers/llama/provider.py
ai_query/providers/openai/__init__.py
ai_query/providers/openai/provider.py
ai_query/providers/openrouter/__init__.py
ai_query/providers/openrouter/provider.py
ai_query/providers/xai/__init__.py
ai_query/providers/xai/provider.py
ai_query-1.6.3.dist-info/METADATA
ai_query-1.6.3.dist-info/WHEEL
ai_query-1.6.3.dist-info/licenses/LICENSE
ai_query-1.6.3.dist-info/RECORD
