Metadata-Version: 2.4
Name: ai-query
Version: 1.6.3
Summary: A unified Python SDK for querying AI models from multiple providers
Project-URL: Homepage, https://github.com/Abdulmumin1/ai-query
Project-URL: Repository, https://github.com/Abdulmumin1/ai-query
License: MIT License
License-File: LICENSE
Requires-Python: >=3.13
Requires-Dist: aiohttp>=3.9.0
Requires-Dist: aiosqlite>=0.20.0
Requires-Dist: mcp>=1.25.0
Provides-Extra: bedrock
Requires-Dist: boto3>=1.34.0; extra == 'bedrock'
Provides-Extra: mcp
Requires-Dist: mcp>=1.0.0; extra == 'mcp'
